{
  "slug": "bard",
  "api_url": "https://api.open5e.com/v1/spelllist/bard/",
  "data": {
    "slug": "bard",
    "name": "bard",
    "desc": "",
    "spells": [
      "abhorrent-apparition",
      "accelerate",
      "adjust-position",
      "agonizing-mark",
      "ale-dritch-blast",
      "ally-aegis",
      "alter-arrows-fortune",
      "analyze-device",
      "anchoring-rope",
      "animal-friendship",
      "animal-messenger",
      "animate-objects",
      "anticipate-attack",
      "anticipate-weakness",
      "arcane-sword",
      "armored-heart",
      "ashen-memories",
      "auspicious-warning",
      "avoid-grievous-injury",
      "awaken",
      "bad-timing",
      "bane",
      "batsense",
      "beguiling-gift",
      "bestow-curse",
      "binding-oath",
      "black-goats-blessing",
      "bleating-call",
      "blindnessdeafness",
      "calm-emotions",
      "charm-person",
      "clairvoyance",
      "comprehend-languages",
      "compulsion",
      "confusion",
      "cure-wounds",
      "dancing-lights",
      "detect-magic",
      "detect-thoughts",
      "dimension-door",
      "disguise-self",
      "dispel-magic",
      "dominate-monster",
      "dominate-person",
      "door-of-the-far-traveler",
      "dream",
      "enhance-ability",
      "enthrall",
      "ethereal-stairs",
      "etherealness",
      "exchanged-knowledge",
      "extract-foyson",
      "eye-bite",
      "eyebite",
      "faerie-fire",
      "fear",
      "feather-fall",
      "feeblemind",
      "find-the-flaw",
      "find-the-path",
      "forcecage",
      "foresight",
      "freedom-of-movement",
      "geas",
      "gift-of-azathoth",
      "glibness",
      "glyph-of-warding",
      "greater-invisibility",
      "greater-restoration",
      "guards-and-wards",
      "hallucinatory-terrain",
      "healing-word",
      "heat-metal",
      "heroism",
      "hideous-laughter",
      "hold-monster",
      "hold-person",
      "hypnagogia",
      "hypnic-jerk",
      "hypnotic-pattern",
      "identify",
      "illusory-script",
      "invisibility",
      "irresistible-dance",
      "jotuns-jest",
      "knock",
      "legend-lore",
      "lesser-restoration",
      "light",
      "locate-animals-or-plants",
      "locate-creature",
      "locate-object",
      "lokis-gift",
      "longstrider",
      "machine-speech",
      "mage-hand",
      "magic-mouth",
      "magnificent-mansion",
      "major-image",
      "mass-cure-wounds",
      "mass-suggestion",
      "mending",
      "message",
      "mind-blank",
      "mind-maze",
      "minor-illusion",
      "mirage-arcane",
      "mirror-realm",
      "mislead",
      "modify-memory",
      "nondetection",
      "obfuscate-object",
      "overclock",
      "planar-binding",
      "plant-growth",
      "polymorph",
      "power-word-kill",
      "power-word-stun",
      "pratfall",
      "prestidigitation",
      "programmed-illusion",
      "project-image",
      "raise-dead",
      "read-memory",
      "regenerate",
      "resurrection",
      "scrying",
      "see-invisibility",
      "seeming",
      "sending",
      "shadows-brand",
      "shatter",
      "silence",
      "silent-image",
      "sleep",
      "soothsayers-shield",
      "soul-of-the-machine",
      "speak-with-animals",
      "speak-with-dead",
      "speak-with-plants",
      "stinking-cloud",
      "subliminal-aversion",
      "suggestion",
      "summon-old-ones-avatar",
      "symbol",
      "teleport",
      "teleportation-circle",
      "thunderwave",
      "timeless-engine",
      "tiny-hut",
      "tongues",
      "true-polymorph",
      "true-seeing",
      "true-strike",
      "unseen-servant",
      "vicious-mockery",
      "winding-key",
      "wotans-rede",
      "write-memory",
      "zone-of-truth"
    ],
    "document__slug": "o5e",
    "document__title": "Open5e Original Content",
    "document__license_url": "http://open5e.com/legal",
    "document__url": "open5e.com"
  }
}